_sxtwl.pyd
sxtwl.py
sxtwl-2.0.7.dist-info/METADATA
sxtwl-2.0.7.dist-info/WHEEL
sxtwl-2.0.7.dist-info/top_level.txt
sxtwl-2.0.7.dist-info/RECORD
