Metadata-Version: 2.1
Name: sxtwl
Version: 2.0.7
Summary: sxtwl_cpp warpper for python
Home-page: https://github.com/yuangu/sxtwl_cpp
Author: yuangu
Author-email: seantone@126.com
License: BSD
Platform: UNKNOWN
